README.md
setup.py
dstat_viz/__init__.py
dstat_viz/main.py
dstat_viz.egg-info/PKG-INFO
dstat_viz.egg-info/SOURCES.txt
dstat_viz.egg-info/dependency_links.txt
dstat_viz.egg-info/entry_points.txt
dstat_viz.egg-info/requires.txt
dstat_viz.egg-info/top_level.txt